odoo/addons/account_move_line_accounting_description/README.rst
odoo/addons/account_move_line_accounting_description/__init__.py
odoo/addons/account_move_line_accounting_description/__manifest__.py
odoo/addons/account_move_line_accounting_description/i18n/account_move_line_accounting_description.pot
odoo/addons/account_move_line_accounting_description/i18n/fr.po
odoo/addons/account_move_line_accounting_description/models/__init__.py
odoo/addons/account_move_line_accounting_description/models/account_move.py
odoo/addons/account_move_line_accounting_description/models/product.py
odoo/addons/account_move_line_accounting_description/readme/CONTRIBUTORS.rst
odoo/addons/account_move_line_accounting_description/readme/DESCRIPTION.rst
odoo/addons/account_move_line_accounting_description/reports/invoice.xml
odoo/addons/account_move_line_accounting_description/static/description/icon.png
odoo/addons/account_move_line_accounting_description/static/description/index.html
odoo/addons/account_move_line_accounting_description/tests/__init__.py
odoo/addons/account_move_line_accounting_description/tests/test_account_move_line_description.py
odoo/addons/account_move_line_accounting_description/views/account_move.xml
odoo/addons/account_move_line_accounting_description/views/product_template.xml
odoo14_addon_account_move_line_accounting_description-14.0.1.0.1.dist-info/METADATA
odoo14_addon_account_move_line_accounting_description-14.0.1.0.1.dist-info/WHEEL
odoo14_addon_account_move_line_accounting_description-14.0.1.0.1.dist-info/top_level.txt
odoo14_addon_account_move_line_accounting_description-14.0.1.0.1.dist-info/RECORD
